LICENSE
MANIFEST.in
README.md
setup.py
django_wechat_sdk.egg-info/PKG-INFO
django_wechat_sdk.egg-info/SOURCES.txt
django_wechat_sdk.egg-info/dependency_links.txt
django_wechat_sdk.egg-info/pbr.json
django_wechat_sdk.egg-info/top_level.txt
djwechat/__init__.py
djwechat/admin.py
djwechat/models.py
djwechat/util.py
docs/Makefile
docs/conf.py
docs/index.rst