Metadata-Version: 1.1
Name: django-wechat-sdk
Version: 0.1
Summary: django-wechat 是一个微信公众号 django 开发库
Home-page: http://github.com/bowenpay/django-wechat/
Author: Jingping Yi
Author-email: jingping.yi@gmail.com
License: BSD License
Platform: UNKNOWN
Classifier: Environment :: Web Environment
Classifier: Framework :: Django
Classifier: Intended Audience :: Developers
Classifier: License :: OSI Approved :: BSD License
Classifier: Operating System :: OS Independent
Classifier: Programming Language :: Python
Classifier: Programming Language :: Python :: 2
Classifier: Programming Language :: Python :: 2.7
Classifier: Topic :: Internet :: WWW/HTTP
Classifier: Topic :: Internet :: WWW/HTTP :: Dynamic Content
